polars_splitters/__init__.py
polars_splitters/core/__init__.py
polars_splitters/core/splitters.py
polars_splitters/utils/__init__.py
polars_splitters/utils/guardrails.py
polars_splitters/utils/type_enforcers.py
polars_splitters/utils/wrapping_helpers.py
polars_splitters-0.4.5.dist-info/METADATA
polars_splitters-0.4.5.dist-info/WHEEL
polars_splitters-0.4.5.dist-info/top_level.txt
polars_splitters-0.4.5.dist-info/RECORD
