Metadata-Version: 2.4
Name: polars-splitters
Version: 0.4.5
Summary: Polars-based splitter functionalities for polars LazyFrames and DataFrames, similar to `sklearn.model_selection.train_test_split` and `sklearn.model_selection.StratifiedKFold`.
Author-email: "Jonas M. Miguel" <charter-shushes0n@icloud.com>
Classifier: License :: OSI Approved :: MIT License
Classifier: Programming Language :: Python
Classifier: Programming Language :: Python :: 3.10
Classifier: Programming Language :: Python :: 3.11
Classifier: Programming Language :: Python :: 3.12
Classifier: Programming Language :: Python :: 3.13
Requires-Python: <3.14,>=3.10
Requires-Dist: loguru==0.7.*
Requires-Dist: polars<1.40,>=1.30
